azure/mgmt/notificationhubs/__init__.py
azure/mgmt/notificationhubs/_configuration.py
azure/mgmt/notificationhubs/_notification_hubs_management_client.py
azure/mgmt/notificationhubs/_patch.py
azure/mgmt/notificationhubs/_vendor.py
azure/mgmt/notificationhubs/_version.py
azure/mgmt/notificationhubs/aio/__init__.py
azure/mgmt/notificationhubs/aio/_configuration.py
azure/mgmt/notificationhubs/aio/_notification_hubs_management_client.py
azure/mgmt/notificationhubs/aio/_patch.py
azure/mgmt/notificationhubs/aio/operations/__init__.py
azure/mgmt/notificationhubs/aio/operations/_namespaces_operations.py
azure/mgmt/notificationhubs/aio/operations/_notification_hubs_operations.py
azure/mgmt/notificationhubs/aio/operations/_operations.py
azure/mgmt/notificationhubs/models/__init__.py
azure/mgmt/notificationhubs/models/_models_py3.py
azure/mgmt/notificationhubs/models/_notification_hubs_management_client_enums.py
azure/mgmt/notificationhubs/operations/__init__.py
azure/mgmt/notificationhubs/operations/_namespaces_operations.py
azure/mgmt/notificationhubs/operations/_notification_hubs_operations.py
azure/mgmt/notificationhubs/operations/_operations.py
azure_mgmt_notificationhubs-8.0.0.dist-info/LICENSE
azure_mgmt_notificationhubs-8.0.0.dist-info/METADATA
azure_mgmt_notificationhubs-8.0.0.dist-info/WHEEL
azure_mgmt_notificationhubs-8.0.0.dist-info/top_level.txt
azure_mgmt_notificationhubs-8.0.0.dist-info/RECORD
